arcade_gui/__init__.py
arcade_gui/core.py
arcade_gui/elements/__init__.py
arcade_gui/elements/flat_button.py
arcade_gui/elements/image_button.py
arcade_gui/elements/inputbox.py
arcade_gui/elements/label.py
arcade_gui/resources/basic_ui_pack/red/red_button00.png
arcade_gui/resources/basic_ui_pack/red/red_button01.png
arcade_gui/resources/basic_ui_pack/red/red_button02.png
arcade_gui/resources/basic_ui_pack/red/red_button03.png
arcade_gui/resources/basic_ui_pack/red/red_button04.png
arcade_gui/resources/basic_ui_pack/red/red_button05.png
arcade_gui/resources/basic_ui_pack/red/red_button06.png
arcade_gui/resources/basic_ui_pack/red/red_button07.png
arcade_gui/resources/basic_ui_pack/red/red_button08.png
arcade_gui/resources/basic_ui_pack/red/red_button09.png
arcade_gui/resources/basic_ui_pack/red/red_button10.png
arcade_gui/resources/basic_ui_pack/red/red_button11.png
arcade_gui/resources/basic_ui_pack/red/red_button12.png
arcade_gui/resources/basic_ui_pack/red/red_button13.png
arcade_gui/resources/style/default.yml
arcade_gui/ui_style.py
arcade_gui/utils.py
arcade_gui-0.1.0a9.dist-info/WHEEL
arcade_gui-0.1.0a9.dist-info/METADATA
arcade_gui-0.1.0a9.dist-info/RECORD
