Metadata-Version: 2.1
Name: arcade-gui
Version: 0.1.0a9
Summary: GUI extension for the Python game library Arcade  https://arcade.academy/
Home-page: https://github.com/eruvanos/arcade_gui
License: MIT
Keywords: arcade,game,gui
Author: Maic Siemering
Author-email: maic@siemering.tech
Requires-Python: >=3.7
Classifier: Development Status :: 2 - Pre-Alpha
Classifier: Intended Audience :: Developers
Classifier: License :: OSI Approved :: MIT License
Classifier: Operating System :: OS Independent
Classifier: Programming Language :: Python
Classifier: Programming Language :: Python :: 3
Classifier: Programming Language :: Python :: 3.7
Classifier: Programming Language :: Python :: 3.8
Classifier: Topic :: Games/Entertainment :: Arcade
Classifier: Topic :: Software Development :: Libraries :: Python Modules
Classifier: Topic :: Software Development :: User Interfaces
Requires-Dist: arcade (>=2.3.15,<3.0.0)
Requires-Dist: pyyaml (>=5.3.1,<6.0.0)
Project-URL: Documentation, https://github.com/eruvanos/arcade_gui
Project-URL: Repository, https://github.com/eruvanos/arcade_gui
